[{ "_id" : { "$oid" : "530124c9f7ec6b6b32d3ae1a" }, "name" : "Brian I. Wagner", "address" : "4901 Vel Rd.", "city" : "Denver", "state" : "CO", "zip" : "23969", "phone" : "1-186-909-3592", "company" : "Aliquam Consulting", "email" : "tristique.ac.eleifend@a.co.uk", "companyFax" : "1-525-876-5880", "companyAddress" : "5627 Egestas St.", "companyCity" : "Fort Collins", "companyState" : "Hawaii", "companyZip" : "23919", "hireDate" : "04/07/2012" },{ "_id" : { "$oid" : "530124c9f7ec6b6b32d3ae1b" }, "name" : "Yael D. Terrell", "address" : "685-8848 Et Av.", "city" : "Tulsa", "state" : "OK", "zip" : "72230", "phone" : "1-433-708-8650", "company" : "Montes PC", "email" : "ac.fermentum@adipiscingelitAliquam.org", "companyFax" : "1-437-180-1562", "companyAddress" : "993-2451 Nec Rd.", "companyCity" : "Broken Arrow", "companyState" : "Georgia", "companyZip" : "45111", "hireDate" : "01/15/2011" },{ "_id" : { "$oid" : "530124c9f7ec6b6b32d3ae1c" }, "name" : "Lyle M. French", "address" : "Ap #667-5769 Nec, Avenue", "city" : "Springfield", "state" : "Missouri", "zip" : "24934", "phone" : "1-971-260-9344", "company" : "Adipiscing Non LLP", "email" : "ut.sem.Nulla@ligulaNullamfeugiat.com", "companyFax" : "1-542-167-0881", "companyAddress" : "687-2736 Sit St.", "companyCity" : "Independence", "companyState" : "Illinois", "companyZip" : "16763", "hireDate" : "09/30/2007" },{ "_id" : { "$oid" : "530124c9f7ec6b6b32d3ae1d" }, "name" : "Emi R. Duran", "address" : "1340 Sociosqu St.", "city" : "Fort Collins", "state" : "Colorado", "zip" : "65169", "phone" : "1-258-889-1542", "company" : "Purus Corp.", "email" : "ornare.In.faucibus@semperrutrum.ca", "companyFax" : "1-492-928-6092", "companyAddress" : "455-965 Cursus Avenue", "companyCity" : "Fort Collins", "companyState" : "Montana", "companyZip" : "56017", "hireDate" : "10/10/2010" },{ "_id" : { "$oid" : "530124c9f7ec6b6b32d3ae1e" }, "name" : "Harriet K. Stout", "address" : "7677 Lectus Av.", "city" : "Grand Island", "state" : "NE", "zip" : "35357", "phone" : "1-319-367-5139", "company" : "Sed Corp.", "email" : "convallis.dolor@Integer.net", "companyFax" : "1-529-935-0362", "companyAddress" : "P.O. Box 832, 3162 Dui. Road", "companyCity" : "Lincoln", "companyState" : "LA", "companyZip" : "20338", "hireDate" : "03/05/2008" },{ "_id" : { "$oid" : "530124c9f7ec6b6b32d3ae1f" }, "name" : "Ann C. Alvarez", "address" : "619-3879 Consequat Rd.", "city" : "Sacramento", "state" : "California", "zip" : "96959", "phone" : "1-735-214-6497", "company" : "Ante Nunc Mauris LLP", "email" : "nec.tempus@variusultrices.org", "companyFax" : "1-918-698-0254", "companyAddress" : "387-5767 Gravida Rd.", "companyCity" : "Los Angeles", "companyState" : "WY", "companyZip" : "94698", "hireDate" : "02/21/2006" },{ "_id" : { "$oid" : "530124c9f7ec6b6b32d3ae20" }, "name" : "Amber R. Horn", "address" : "359-2902 Sed Av.", "city" : "Springdale", "state" : "Arkansas", "zip" : "72816", "phone" : "1-749-790-1066", "company" : "Nullam Ut Corporation", "email" : "orci.Ut@velitPellentesqueultricies.edu", "companyFax" : "1-529-627-4625", "companyAddress" : "Ap #386-2620 Vivamus Road", "companyCity" : "Fayetteville", "companyState" : "MT", "companyZip" : "71861", "hireDate" : "12/09/2008" },{ "_id" : { "$oid" : "530124c9f7ec6b6b32d3ae21" }, "name" : "Vera F. Mcbride", "address" : "8231 Pede. Rd.", "city" : "South Bend", "state" : "Indiana", "zip" : "15140", "phone" : "1-651-418-7708", "company" : "Eros Ltd", "email" : "vitae.orci@orciUt.com", "companyFax" : "1-778-642-1795", "companyAddress" : "3653 Lorem, Road", "companyCity" : "Fort Wayne", "companyState" : "ID", "companyZip" : "26140", "hireDate" : "11/27/2010" },{ "_id" : { "$oid" : "530124c9f7ec6b6b32d3ae22" }, "name" : "Wallace Q. Hansen", "address" : "Ap #305-8844 Sed Rd.", "city" : "Idaho Falls", "state" : "Idaho", "zip" : "14754", "phone" : "1-939-443-7718", "company" : "Pellentesque Sed Dictum Institute", "email" : "Cras.convallis.convallis@pede.ca", "companyFax" : "1-726-980-5835", "companyAddress" : "4390 Integer St.", "companyCity" : "Nampa", "companyState" : "AL", "companyZip" : "93145", "hireDate" : "04/09/2009" },{ "_id" : { "$oid" : "530124c9f7ec6b6b32d3ae23" }, "name" : "Amena T. Ortega", "address" : "P.O. Box 569, 2610 Sapien Rd.", "city" : "Juneau", "state" : "AK", "zip" : "99573", "phone" : "1-186-961-2109", "company" : "A Limited", "email" : "non.enim.Mauris@enimNunc.ca", "companyFax" : "1-520-201-9548", "companyAddress" : "7279 Aliquam Rd.", "companyCity" : "College", "companyState" : "Maine", "companyZip" : "99770", "hireDate" : "09/21/2009" },{ "_id" : { "$oid" : "530124c9f7ec6b6b32d3ae24" }, "name" : "Jenette J. Farrell", "address" : "P.O. Box 842, 380 Sed St.", "city" : "Nampa", "state" : "ID", "zip" : "10153", "phone" : "1-483-430-9123", "company" : "Vel Venenatis Corporation", "email" : "at.auctor.ullamcorper@nisidictumaugue.co.uk", "companyFax" : "1-177-980-4274", "companyAddress" : "7936 Velit. Avenue", "companyCity" : "Pocatello", "companyState" : "AZ", "companyZip" : "47772", "hireDate" : "07/27/2006" },{ "_id" : { "$oid" : "530124c9f7ec6b6b32d3ae25" }, "name" : "Mira Q. Medina", "address" : "P.O. Box 902, 9340 Phasellus Rd.", "city" : "Jacksonville", "state" : "Florida", "zip" : "95635", "phone" : "1-474-897-6467", "company" : "Mauris Aliquam Limited", "email" : "magna.sed@ultricesVivamusrhoncus.org", "companyFax" : "1-351-871-8397", "companyAddress" : "P.O. Box 650, 9165 Mattis. St.", "companyCity" : "Jacksonville", "companyState" : "Oklahoma", "companyZip" : "19408", "hireDate" : "05/15/2011" },{ "_id" : { "$oid" : "530124c9f7ec6b6b32d3ae26" }, "name" : "Sloane G. Patrick", "address" : "P.O. Box 693, 8892 Sed Ave", "city" : "Overland Park", "state" : "Kansas", "zip" : "70403", "phone" : "1-620-114-4621", "company" : "Erat Industries", "email" : "tellus.imperdiet@necdiamDuis.com", "companyFax" : "1-681-212-5611", "companyAddress" : "769-8936 Quisque Av.", "companyCity" : "Wichita", "companyState" : "Idaho", "companyZip" : "45655", "hireDate" : "06/20/2009" },{ "_id" : { "$oid" : "530124c9f7ec6b6b32d3ae27" }, "name" : "Preston O. Ortega", "address" : "Ap #373-9959 Vestibulum Avenue", "city" : "St. Petersburg", "state" : "FL", "zip" : "65823", "phone" : "1-956-649-1091", "company" : "Curabitur Vel Lectus Associates", "email" : "justo@turpis.net", "companyFax" : "1-625-977-5700", "companyAddress" : "P.O. Box 138, 2682 Penatibus Avenue", "companyCity" : "Miami", "companyState" : "Iowa", "companyZip" : "33438", "hireDate" : "06/19/2005" },{ "_id" : { "$oid" : "530124c9f7ec6b6b32d3ae28" }, "name" : "Nathaniel U. Mcclain", "address" : "2614 Euismod St.", "city" : "Akron", "state" : "Ohio", "zip" : "99155", "phone" : "1-871-145-3259", "company" : "Eu Ltd", "email" : "imperdiet.nec.leo@idante.org", "companyFax" : "1-694-727-7256", "companyAddress" : "Ap #450-5868 Et Road", "companyCity" : "Toledo", "companyState" : "ID", "companyZip" : "89380", "hireDate" : "12/02/2007" },{ "_id" : { "$oid" : "530124c9f7ec6b6b32d3ae29" }, "name" : "Vance D. Finch", "address" : "P.O. Box 265, 1407 Eu, Road", "city" : "Rochester", "state" : "Minnesota", "zip" : "50996", "phone" : "1-360-419-3552", "company" : "Eros Foundation", "email" : "molestie.arcu.Sed@Vivamussit.net", "companyFax" : "1-928-726-8681", "companyAddress" : "Ap #685-3292 Cras Avenue", "companyCity" : "Duluth", "companyState" : "Missouri", "companyZip" : "69728", "hireDate" : "06/05/2005" },{ "_id" : { "$oid" : "530124c9f7ec6b6b32d3ae2a" }, "name" : "Gabriel C. Butler", "address" : "P.O. Box 304, 4102 Nisi. Ave", "city" : "Clarksville", "state" : "Tennessee", "zip" : "72522", "phone" : "1-638-982-2474", "company" : "Nunc Ullamcorper Limited", "email" : "odio@cursus.ca", "companyFax" : "1-735-561-6992", "companyAddress" : "546-562 Risus. St.", "companyCity" : "Clarksville", "companyState" : "ID", "companyZip" : "35866", "hireDate" : "08/29/2007" },{ "_id" : { "$oid" : "530124c9f7ec6b6b32d3ae2b" }, "name" : "Angela M. Long", "address" : "4776 Ut St.", "city" : "Gary", "state" : "IN", "zip" : "66818", "phone" : "1-260-957-9876", "company" : "Molestie Dapibus Corporation", "email" : "Nulla.facilisi@bibendumfermentummetus.co.uk", "companyFax" : "1-884-189-6316", "companyAddress" : "P.O. Box 904, 6826 Ipsum Street", "companyCity" : "Fort Wayne", "companyState" : "Alabama", "companyZip" : "40594", "hireDate" : "01/29/2009" },{ "_id" : { "$oid" : "530124c9f7ec6b6b32d3ae2c" }, "name" : "Haviva H. Bolton", "address" : "P.O. Box 805, 1925 Elit, Street", "city" : "Nashville", "state" : "Tennessee", "zip" : "96381", "phone" : "1-405-848-4510", "company" : "Blandit Foundation", "email" : "Nullam.scelerisque.neque@blanditat.co.uk", "companyFax" : "1-975-428-7016", "companyAddress" : "674-9519 Magna. Rd.", "companyCity" : "Clarksville", "companyState" : "AZ", "companyZip" : "17825", "hireDate" : "10/12/2005" },{ "_id" : { "$oid" : "530124c9f7ec6b6b32d3ae2d" }, "name" : "Moses S. Kemp", "address" : "7938 Sodales Av.", "city" : "Kansas City", "state" : "Kansas", "zip" : "60205", "phone" : "1-784-808-2231", "company" : "Adipiscing Company", "email" : "tellus.sem@nasceturridiculus.co.uk", "companyFax" : "1-264-873-5959", "companyAddress" : "3488 Cum Street", "companyCity" : "Olathe", "companyState" : "IA", "companyZip" : "47196", "hireDate" : "05/08/2013" },{ "_id" : { "$oid" : "530124c9f7ec6b6b32d3ae2e" }, "name" : "Mercedes K. Dillon", "address" : "5766 Mollis. Avenue", "city" : "Atlanta", "state" : "GA", "zip" : "33414", "phone" : "1-963-932-7732", "company" : "Sed Nulla LLP", "email" : "vestibulum@a.edu", "companyFax" : "1-225-110-3479", "companyAddress" : "525-5070 Vitae Street", "companyCity" : "Atlanta", "companyState" : "PA", "companyZip" : "70146", "hireDate" : "01/07/2011" },{ "_id" : { "$oid" : "530124c9f7ec6b6b32d3ae2f" }, "name" : "Orlando I. Mcdowell", "address" : "P.O. Box 548, 2807 Neque Road", "city" : "Overland Park", "state" : "KS", "zip" : "58968", "phone" : "1-137-769-6944", "company" : "Felis Ullamcorper Viverra LLP", "email" : "in.aliquet.lobortis@turpis.ca", "companyFax" : "1-964-394-0585", "companyAddress" : "5544 Vitae Rd.", "companyCity" : "Overland Park", "companyState" : "Tennessee", "companyZip" : "25866", "hireDate" : "03/16/2011" },{ "_id" : { "$oid" : "530124c9f7ec6b6b32d3ae30" }, "name" : "Driscoll X. Conrad", "address" : "P.O. Box 688, 2248 Lorem Av.", "city" : "Gaithersburg", "state" : "Maryland", "zip" : "39351", "phone" : "1-580-907-3592", "company" : "Consectetuer Mauris Id Incorporated", "email" : "magnis.dis@Cum.co.uk", "companyFax" : "1-450-735-7073", "companyAddress" : "Ap #574-9833 Nunc Avenue", "companyCity" : "Annapolis", "companyState" : "Mississippi", "companyZip" : "51490", "hireDate" : "11/12/2005" },{ "_id" : { "$oid" : "530124c9f7ec6b6b32d3ae31" }, "name" : "Lysandra J. Joyce", "address" : "585-6877 Ut Street", "city" : "Tuscaloosa", "state" : "Alabama", "zip" : "35207", "phone" : "1-383-937-4291", "company" : "Et Ltd", "email" : "ornare@etcommodo.co.uk", "companyFax" : "1-256-470-6234", "companyAddress" : "P.O. Box 329, 7626 Risus. Ave", "companyCity" : "Mobile", "companyState" : "ID", "companyZip" : "35628", "hireDate" : "07/23/2013" },{ "_id" : { "$oid" : "530124c9f7ec6b6b32d3ae32" }, "name" : "Nathan L. Clay", "address" : "P.O. Box 985, 2849 Odio Avenue", "city" : "Memphis", "state" : "TN", "zip" : "89278", "phone" : "1-958-594-0460", "company" : "Ultrices Sit Ltd", "email" : "molestie.in@luctusutpellentesque.ca", "companyFax" : "1-685-635-9143", "companyAddress" : "673-6850 Urna Ave", "companyCity" : "Clarksville", "companyState" : "AL", "companyZip" : "90565", "hireDate" : "09/06/2006" },{ "_id" : { "$oid" : "530124c9f7ec6b6b32d3ae33" }, "name" : "Iliana J. Barrett", "address" : "Ap #640-6223 Parturient Street", "city" : "Shreveport", "state" : "LA", "zip" : "59511", "phone" : "1-554-393-3637", "company" : "Est Tempor Bibendum Associates", "email" : "iaculis.enim.sit@sapien.org", "companyFax" : "1-494-230-7060", "companyAddress" : "Ap #318-9037 Aliquam Road", "companyCity" : "Metairie", "companyState" : "WA", "companyZip" : "37237", "hireDate" : "11/08/2008" },{ "_id" : { "$oid" : "530124c9f7ec6b6b32d3ae34" }, "name" : "Tanya H. Swanson", "address" : "P.O. Box 469, 9025 Consectetuer St.", "city" : "Tulsa", "state" : "OK", "zip" : "67284", "phone" : "1-263-354-9591", "company" : "Mauris Sagittis Placerat Limited", "email" : "at.iaculis.quis@consectetueradipiscing.co.uk", "companyFax" : "1-182-940-6720", "companyAddress" : "P.O. Box 970, 9314 Etiam St.", "companyCity" : "Tulsa", "companyState" : "TN", "companyZip" : "51272", "hireDate" : "03/08/2009" },{ "_id" : { "$oid" : "530124c9f7ec6b6b32d3ae35" }, "name" : "Kamal Z. Clarke", "address" : "693-2590 Volutpat Rd.", "city" : "Cambridge", "state" : "Massachusetts", "zip" : "20129", "phone" : "1-356-683-2154", "company" : "Ut Limited", "email" : "nec@nonummy.net", "companyFax" : "1-575-972-1840", "companyAddress" : "Ap #907-3713 Libero. Street", "companyCity" : "Boston", "companyState" : "Hawaii", "companyZip" : "12649", "hireDate" : "01/25/2006" },{ "_id" : { "$oid" : "530124c9f7ec6b6b32d3ae36" }, "name" : "Shad Z. Robinson", "address" : "P.O. Box 417, 4664 Tincidunt Street", "city" : "Olympia", "state" : "Washington", "zip" : "41550", "phone" : "1-675-481-4156", "company" : "Dui In Sodales Ltd", "email" : "Sed.eu.eros@disparturient.net", "companyFax" : "1-914-529-4196", "companyAddress" : "9117 Amet St.", "companyCity" : "Seattle", "companyState" : "Texas", "companyZip" : "76537", "hireDate" : "07/26/2006" },{ "_id" : { "$oid" : "530124c9f7ec6b6b32d3ae37" }, "name" : "Allen X. Austin", "address" : "P.O. Box 990, 2746 Nec Avenue", "city" : "St. Petersburg", "state" : "FL", "zip" : "58340", "phone" : "1-881-421-3886", "company" : "Arcu Incorporated", "email" : "montes@mifelisadipiscing.org", "companyFax" : "1-729-570-3788", "companyAddress" : "P.O. Box 809, 6633 Pharetra Avenue", "companyCity" : "Orlando", "companyState" : "AZ", "companyZip" : "27023", "hireDate" : "12/10/2009" },{ "_id" : { "$oid" : "530124c9f7ec6b6b32d3ae38" }, "name" : "Gemma G. Benjamin", "address" : "Ap #922-109 Amet Street", "city" : "Hilo", "state" : "HI", "zip" : "63959", "phone" : "1-658-118-1544", "company" : "Ac Nulla In Inc.", "email" : "pretium@velvulputate.net", "companyFax" : "1-825-729-4004", "companyAddress" : "638-7419 Ipsum Street", "companyCity" : "Honolulu", "companyState" : "NV", "companyZip" : "82850", "hireDate" : "12/27/2011" },{ "_id" : { "$oid" : "530124c9f7ec6b6b32d3ae39" }, "name" : "Oliver O. Kelley", "address" : "Ap #629-7052 Proin Rd.", "city" : "Columbia", "state" : "Missouri", "zip" : "51087", "phone" : "1-312-380-3170", "company" : "Cras Corp.", "email" : "hendrerit@MorbivehiculaPellentesque.ca", "companyFax" : "1-181-889-8040", "companyAddress" : "Ap #248-3025 Eu Avenue", "companyCity" : "Springfield", "companyState" : "Nevada", "companyZip" : "89109", "hireDate" : "09/12/2010" },{ "_id" : { "$oid" : "530124c9f7ec6b6b32d3ae3a" }, "name" : "Nathan K. Adkins", "address" : "144-8373 Semper Av.", "city" : "Chattanooga", "state" : "TN", "zip" : "86812", "phone" : "1-959-389-2475", "company" : "Diam Sed Corporation", "email" : "parturient.montes.nascetur@molestie.net", "companyFax" : "1-165-192-0073", "companyAddress" : "1592 Odio Rd.", "companyCity" : "Knoxville", "companyState" : "Alabama", "companyZip" : "94783", "hireDate" : "07/02/2010" },{ "_id" : { "$oid" : "530124c9f7ec6b6b32d3ae3b" }, "name" : "Alden L. Newman", "address" : "Ap #548-8202 Urna, Street", "city" : "Georgia", "state" : "GA", "zip" : "90081", "phone" : "1-758-869-0313", "company" : "Nisi Magna Sed Corporation", "email" : "diam.luctus.lobortis@Crasloremlorem.ca", "companyFax" : "1-206-965-8037", "companyAddress" : "P.O. Box 465, 2822 Augue St.", "companyCity" : "Columbus", "companyState" : "OK", "companyZip" : "51162", "hireDate" : "10/06/2006" },{ "_id" : { "$oid" : "530124c9f7ec6b6b32d3ae3c" }, "name" : "Preston Z. Morrison", "address" : "2099 Lectus, Ave", "city" : "Owensboro", "state" : "Kentucky", "zip" : "25946", "phone" : "1-103-855-1282", "company" : "Vitae Orci Ltd", "email" : "Suspendisse.dui@diamnuncullamcorper.com", "companyFax" : "1-348-158-0536", "companyAddress" : "P.O. Box 369, 1175 Nonummy Avenue", "companyCity" : "Lexington", "companyState" : "KY", "companyZip" : "50963", "hireDate" : "07/11/2008" },{ "_id" : { "$oid" : "530124c9f7ec6b6b32d3ae3d" }, "name" : "Quinn N. Hickman", "address" : "730-7579 Dolor, Avenue", "city" : "Olathe", "state" : "KS", "zip" : "42391", "phone" : "1-424-874-8924", "company" : "Gravida Nunc Industries", "email" : "massa@Aenean.com", "companyFax" : "1-994-410-6232", "companyAddress" : "1295 Nulla Road", "companyCity" : "Olathe", "companyState" : "NV", "companyZip" : "56319", "hireDate" : "01/05/2013" },{ "_id" : { "$oid" : "530124c9f7ec6b6b32d3ae3e" }, "name" : "Sydnee U. Blankenship", "address" : "Ap #172-2515 Eu Rd.", "city" : "Phoenix", "state" : "AZ", "zip" : "85439", "phone" : "1-611-409-4195", "company" : "Feugiat Tellus Lorem Consulting", "email" : "euismod.enim@turpisNullaaliquet.ca", "companyFax" : "1-699-555-7224", "companyAddress" : "Ap #692-3521 Mi Rd.", "companyCity" : "Glendale", "companyState" : "Mississippi", "companyZip" : "85951", "hireDate" : "01/10/2012" },{ "_id" : { "$oid" : "530124c9f7ec6b6b32d3ae3f" }, "name" : "Lars V. Whitley", "address" : "721-5907 Dictum Rd.", "city" : "Hilo", "state" : "Hawaii", "zip" : "40318", "phone" : "1-249-379-3296", "company" : "Nunc Commodo PC", "email" : "in.sodales@ornareFusce.com", "companyFax" : "1-652-619-0679", "companyAddress" : "Ap #594-507 Lacus Road", "companyCity" : "Honolulu", "companyState" : "TX", "companyZip" : "21270", "hireDate" : "12/10/2007" },{ "_id" : { "$oid" : "530124c9f7ec6b6b32d3ae40" }, "name" : "Todd C. Petersen", "address" : "1715 Erat Ave", "city" : "Fairbanks", "state" : "Alaska", "zip" : "99983", "phone" : "1-960-703-9713", "company" : "Aenean Foundation", "email" : "ante.lectus@felisorciadipiscing.edu", "companyFax" : "1-798-404-8597", "companyAddress" : "517-7823 Erat, Ave", "companyCity" : "Fairbanks", "companyState" : "KS", "companyZip" : "99610", "hireDate" : "06/02/2011" },{ "_id" : { "$oid" : "530124c9f7ec6b6b32d3ae41" }, "name" : "Adam I. Compton", "address" : "7837 Cubilia Rd.", "city" : "Milwaukee", "state" : "WI", "zip" : "38720", "phone" : "1-400-606-6971", "company" : "Fermentum Metus Aenean Corporation", "email" : "odio@erosProin.org", "companyFax" : "1-471-860-0250", "companyAddress" : "829 Arcu. Ave", "companyCity" : "Milwaukee", "companyState" : "MT", "companyZip" : "42456", "hireDate" : "03/15/2005" },{ "_id" : { "$oid" : "530124c9f7ec6b6b32d3ae42" }, "name" : "Lane E. Porter", "address" : "P.O. Box 217, 1587 Iaculis Av.", "city" : "Glendale", "state" : "Arizona", "zip" : "85973", "phone" : "1-862-271-1919", "company" : "Turpis Egestas Aliquam Corporation", "email" : "Donec.nibh.Quisque@Mauris.org", "companyFax" : "1-490-307-6154", "companyAddress" : "Ap #614-193 Aliquam St.", "companyCity" : "Tucson", "companyState" : "Nevada", "companyZip" : "85202", "hireDate" : "05/23/2006" },{ "_id" : { "$oid" : "530124c9f7ec6b6b32d3ae43" }, "name" : "Celeste N. Gould", "address" : "114-557 Orci Rd.", "city" : "Tampa", "state" : "Florida", "zip" : "67989", "phone" : "1-520-935-4057", "company" : "Odio Nam Foundation", "email" : "Donec@amet.ca", "companyFax" : "1-890-986-2539", "companyAddress" : "2617 Eget, Av.", "companyCity" : "Orlando", "companyState" : "NE", "companyZip" : "97627", "hireDate" : "05/07/2009" },{ "_id" : { "$oid" : "530124c9f7ec6b6b32d3ae44" }, "name" : "Imelda C. Sweet", "address" : "Ap #489-1771 Neque Road", "city" : "Athens", "state" : "Georgia", "zip" : "40188", "phone" : "1-492-812-4447", "company" : "Amet Inc.", "email" : "ultrices@sedliberoProin.ca", "companyFax" : "1-933-395-4680", "companyAddress" : "562-2911 Cursus Rd.", "companyCity" : "Savannah", "companyState" : "Delaware", "companyZip" : "39437", "hireDate" : "12/22/2012" },{ "_id" : { "$oid" : "530124c9f7ec6b6b32d3ae45" }, "name" : "Abra J. Patel", "address" : "7412 Nam Rd.", "city" : "Fayetteville", "state" : "AR", "zip" : "71161", "phone" : "1-379-605-2849", "company" : "Convallis Inc.", "email" : "elementum.lorem.ut@ornareliberoat.edu", "companyFax" : "1-158-841-9760", "companyAddress" : "234-6548 Imperdiet, Avenue", "companyCity" : "Fort Smith", "companyState" : "IN", "companyZip" : "72229", "hireDate" : "10/02/2005" },{ "_id" : { "$oid" : "530124c9f7ec6b6b32d3ae46" }, "name" : "Amir T. Wallace", "address" : "P.O. Box 275, 6741 Eget Avenue", "city" : "Wilmington", "state" : "Delaware", "zip" : "35694", "phone" : "1-479-267-9695", "company" : "Molestie Sed Foundation", "email" : "pede@elitpharetraut.org", "companyFax" : "1-858-918-8495", "companyAddress" : "660-3549 Phasellus Road", "companyCity" : "Dover", "companyState" : "Maryland", "companyZip" : "94149", "hireDate" : "12/02/2006" },{ "_id" : { "$oid" : "530124c9f7ec6b6b32d3ae47" }, "name" : "Elliott S. Edwards", "address" : "Ap #584-3006 Quisque Av.", "city" : "Overland Park", "state" : "KS", "zip" : "15641", "phone" : "1-187-930-4098", "company" : "Feugiat Sed Company", "email" : "Morbi@vel.edu", "companyFax" : "1-525-354-7967", "companyAddress" : "P.O. Box 384, 472 Consectetuer Road", "companyCity" : "Topeka", "companyState" : "IN", "companyZip" : "95366", "hireDate" : "06/03/2010" },{ "_id" : { "$oid" : "530124c9f7ec6b6b32d3ae48" }, "name" : "Addison Q. Hendricks", "address" : "Ap #175-3721 Amet Av.", "city" : "Rockville", "state" : "Maryland", "zip" : "46419", "phone" : "1-690-538-5775", "company" : "Nonummy Ut Molestie Associates", "email" : "dictum@penatibus.co.uk", "companyFax" : "1-181-611-5083", "companyAddress" : "Ap #211-372 Lectus. Avenue", "companyCity" : "Gaithersburg", "companyState" : "Maryland", "companyZip" : "90287", "hireDate" : "06/08/2012" },{ "_id" : { "$oid" : "530124c9f7ec6b6b32d3ae49" }, "name" : "Nigel R. Matthews", "address" : "P.O. Box 720, 6074 Dui Av.", "city" : "Kearney", "state" : "NE", "zip" : "41282", "phone" : "1-318-172-1605", "company" : "Mollis Dui In Limited", "email" : "Donec.egestas@acrisus.org", "companyFax" : "1-576-283-4817", "companyAddress" : "3581 Justo. Ave", "companyCity" : "Kearney", "companyState" : "Indiana", "companyZip" : "26365", "hireDate" : "08/26/2009" },{ "_id" : { "$oid" : "530124c9f7ec6b6b32d3ae4a" }, "name" : "Graham V. Melton", "address" : "2715 Metus. Rd.", "city" : "Sacramento", "state" : "CA", "zip" : "90273", "phone" : "1-432-506-8568", "company" : "Nec Enim Nunc Incorporated", "email" : "sed.sem.egestas@enimdiamvel.edu", "companyFax" : "1-543-563-4495", "companyAddress" : "4911 Feugiat Street", "companyCity" : "Sacramento", "companyState" : "Colorado", "companyZip" : "92693", "hireDate" : "06/20/2005" },{ "_id" : { "$oid" : "530124c9f7ec6b6b32d3ae4b" }, "name" : "Kane L. Ellis", "address" : "464-6286 Quam Street", "city" : "Olathe", "state" : "KS", "zip" : "71945", "phone" : "1-200-926-5901", "company" : "Nulla Inc.", "email" : "enim.Curabitur@nibhAliquam.co.uk", "companyFax" : "1-857-423-8579", "companyAddress" : "7196 Pede Av.", "companyCity" : "Kansas City", "companyState" : "VT", "companyZip" : "77753", "hireDate" : "12/24/2008" },{ "_id" : { "$oid" : "530124c9f7ec6b6b32d3ae4c" }, "name" : "Rinah C. Hahn", "address" : "267-3306 Et St.", "city" : "Cleveland", "state" : "OH", "zip" : "14710", "phone" : "1-543-839-2679", "company" : "Vitae Ltd", "email" : "eget@nec.edu", "companyFax" : "1-143-445-0100", "companyAddress" : "Ap #192-4999 Elementum, St.", "companyCity" : "Cleveland", "companyState" : "Colorado", "companyZip" : "33450", "hireDate" : "08/05/2013" },{ "_id" : { "$oid" : "530124c9f7ec6b6b32d3ae4d" }, "name" : "Quail V. Knapp", "address" : "Ap #263-3062 Velit. Street", "city" : "Reno", "state" : "Nevada", "zip" : "90613", "phone" : "1-146-731-0816", "company" : "Turpis Industries", "email" : "lorem.tristique@condimentumDonec.org", "companyFax" : "1-634-242-8801", "companyAddress" : "999-1740 Sed Rd.", "companyCity" : "Paradise", "companyState" : "AZ", "companyZip" : "58133", "hireDate" : "03/19/2011" },{ "_id" : { "$oid" : "530124c9f7ec6b6b32d3ae4e" }, "name" : "Jessamine J. Stephenson", "address" : "Ap #287-3194 Nec Rd.", "city" : "Austin", "state" : "TX", "zip" : "47916", "phone" : "1-396-660-8597", "company" : "Vel Est Tempor Institute", "email" : "lorem.lorem@velitPellentesque.ca", "companyFax" : "1-665-781-2588", "companyAddress" : "4631 Sem Rd.", "companyCity" : "San Antonio", "companyState" : "Utah", "companyZip" : "79109", "hireDate" : "05/31/2009" },{ "_id" : { "$oid" : "530124c9f7ec6b6b32d3ae4f" }, "name" : "Blair Q. Parker", "address" : "P.O. Box 542, 7397 Sed St.", "city" : "West Jordan", "state" : "Utah", "zip" : "56714", "phone" : "1-990-846-0004", "company" : "A Mi Foundation", "email" : "condimentum.eget@ligula.edu", "companyFax" : "1-546-190-9045", "companyAddress" : "8297 Nisl Avenue", "companyCity" : "Provo", "companyState" : "MN", "companyZip" : "96130", "hireDate" : "01/11/2010" },{ "_id" : { "$oid" : "530124c9f7ec6b6b32d3ae50" }, "name" : "Elizabeth V. Mcleod", "address" : "P.O. Box 292, 644 Dictum. Road", "city" : "Grand Island", "state" : "NE", "zip" : "80385", "phone" : "1-618-455-8256", "company" : "Ultrices Sit Amet Ltd", "email" : "vitae.velit@veliteu.net", "companyFax" : "1-349-687-8479", "companyAddress" : "P.O. Box 378, 8684 Feugiat Avenue", "companyCity" : "Lincoln", "companyState" : "Ohio", "companyZip" : "99541", "hireDate" : "09/25/2012" },{ "_id" : { "$oid" : "530124c9f7ec6b6b32d3ae51" }, "name" : "Lee H. Robinson", "address" : "Ap #430-7095 Curabitur Av.", "city" : "Savannah", "state" : "GA", "zip" : "21647", "phone" : "1-390-666-6675", "company" : "Suspendisse Non Limited", "email" : "elit.elit.fermentum@Sednunc.co.uk", "companyFax" : "1-734-281-0295", "companyAddress" : "202-8008 Semper Road", "companyCity" : "Columbus", "companyState" : "Missouri", "companyZip" : "79940", "hireDate" : "06/10/2010" },{ "_id" : { "$oid" : "530124c9f7ec6b6b32d3ae52" }, "name" : "Neville K. Knapp", "address" : "Ap #860-4685 Cras Rd.", "city" : "Jackson", "state" : "MS", "zip" : "33596", "phone" : "1-117-591-9448", "company" : "Vivamus Rhoncus Donec PC", "email" : "tristique.senectus@dignissim.org", "companyFax" : "1-585-372-8846", "companyAddress" : "Ap #147-9616 Nisi. Road", "companyCity" : "Jackson", "companyState" : "DE", "companyZip" : "59191", "hireDate" : "04/16/2007" },{ "_id" : { "$oid" : "530124c9f7ec6b6b32d3ae53" }, "name" : "Desirae K. Warner", "address" : "958-3314 Turpis. Av.", "city" : "Evansville", "state" : "IN", "zip" : "63799", "phone" : "1-805-800-9007", "company" : "Convallis Est Company", "email" : "aliquet@nec.ca", "companyFax" : "1-498-679-7314", "companyAddress" : "278-6155 Ligula. Avenue", "companyCity" : "Indianapolis", "companyState" : "Virginia", "companyZip" : "91411", "hireDate" : "06/01/2008" },{ "_id" : { "$oid" : "530124c9f7ec6b6b32d3ae54" }, "name" : "Carlos F. Reed", "address" : "P.O. Box 830, 9192 Suspendisse Avenue", "city" : "Naperville", "state" : "IL", "zip" : "37473", "phone" : "1-525-117-3131", "company" : "Litora Torquent Corp.", "email" : "natoque@ultrices.ca", "companyFax" : "1-570-300-3251", "companyAddress" : "2335 Cum Rd.", "companyCity" : "Joliet", "companyState" : "Minnesota", "companyZip" : "38329", "hireDate" : "01/23/2011" },{ "_id" : { "$oid" : "530124c9f7ec6b6b32d3ae55" }, "name" : "Lawrence Q. Mooney", "address" : "568-7987 In Rd.", "city" : "Rutland", "state" : "VT", "zip" : "74363", "phone" : "1-799-660-5726", "company" : "Risus Varius Associates", "email" : "est.tempor@inceptoshymenaeosMauris.ca", "companyFax" : "1-901-345-0713", "companyAddress" : "197 Sed, Av.", "companyCity" : "Rutland", "companyState" : "Louisiana", "companyZip" : "66064", "hireDate" : "05/07/2009" },{ "_id" : { "$oid" : "530124c9f7ec6b6b32d3ae56" }, "name" : "Hasad P. Dejesus", "address" : "Ap #505-8828 Ipsum St.", "city" : "Casper", "state" : "WY", "zip" : "94841", "phone" : "1-487-934-0427", "company" : "Mollis Phasellus Associates", "email" : "aliquet@tincidunttempus.org", "companyFax" : "1-408-711-6853", "companyAddress" : "440-8894 Cursus Av.", "companyCity" : "Wyoming", "companyState" : "AK", "companyZip" : "35560", "hireDate" : "08/15/2008" },{ "_id" : { "$oid" : "530124c9f7ec6b6b32d3ae57" }, "name" : "Noel T. Aguirre", "address" : "Ap #563-4809 Est, St.", "city" : "Louisville", "state" : "KY", "zip" : "40364", "phone" : "1-534-828-4034", "company" : "Ante Bibendum Inc.", "email" : "nec.ligula.consectetuer@ut.ca", "companyFax" : "1-605-642-7592", "companyAddress" : "P.O. Box 683, 6557 Id Road", "companyCity" : "Owensboro", "companyState" : "Arizona", "companyZip" : "20623", "hireDate" : "03/10/2007" },{ "_id" : { "$oid" : "530124c9f7ec6b6b32d3ae58" }, "name" : "Michael B. Lopez", "address" : "P.O. Box 391, 5144 Consequat Street", "city" : "Salem", "state" : "Oregon", "zip" : "50239", "phone" : "1-704-169-8713", "company" : "Et Tristique Pellentesque Foundation", "email" : "Suspendisse@Quisque.net", "companyFax" : "1-139-603-0426", "companyAddress" : "212-5855 Dui. St.", "companyCity" : "Hillsboro", "companyState" : "CA", "companyZip" : "54977", "hireDate" : "12/17/2009" },{ "_id" : { "$oid" : "530124c9f7ec6b6b32d3ae59" }, "name" : "Cody U. Kidd", "address" : "5846 Nunc, Av.", "city" : "Minneapolis", "state" : "Minnesota", "zip" : "35988", "phone" : "1-307-564-0310", "company" : "Integer LLP", "email" : "Etiam.laoreet@urna.net", "companyFax" : "1-314-873-9353", "companyAddress" : "8640 Magna. Avenue", "companyCity" : "Saint Paul", "companyState" : "ME", "companyZip" : "71823", "hireDate" : "06/01/2011" },{ "_id" : { "$oid" : "530124c9f7ec6b6b32d3ae5a" }, "name" : "Ciara C. Whitley", "address" : "291-4624 Amet Rd.", "city" : "Newark", "state" : "DE", "zip" : "11125", "phone" : "1-785-885-2129", "company" : "Enim PC", "email" : "aliquet@estMauriseu.edu", "companyFax" : "1-197-683-8830", "companyAddress" : "P.O. Box 769, 6610 Neque St.", "companyCity" : "Wilmington", "companyState" : "AR", "companyZip" : "75356", "hireDate" : "06/12/2010" },{ "_id" : { "$oid" : "530124c9f7ec6b6b32d3ae5b" }, "name" : "Lyle W. Berry", "address" : "932-246 Porta Avenue", "city" : "Tulsa", "state" : "OK", "zip" : "49333", "phone" : "1-765-183-2418", "company" : "Et Corp.", "email" : "Praesent.interdum.ligula@leo.co.uk", "companyFax" : "1-148-599-1630", "companyAddress" : "P.O. Box 174, 6840 Auctor Rd.", "companyCity" : "Tulsa", "companyState" : "GA", "companyZip" : "38425", "hireDate" : "01/01/2006" },{ "_id" : { "$oid" : "530124c9f7ec6b6b32d3ae5c" }, "name" : "Lael P. Jimenez", "address" : "9635 Dui. St.", "city" : "Carson City", "state" : "Nevada", "zip" : "73642", "phone" : "1-542-242-9000", "company" : "Aptent Taciti Inc.", "email" : "pede.Praesent.eu@acliberonec.net", "companyFax" : "1-238-156-1516", "companyAddress" : "Ap #682-4839 Aliquam, Road", "companyCity" : "Reno", "companyState" : "TX", "companyZip" : "77774", "hireDate" : "12/25/2007" },{ "_id" : { "$oid" : "530124c9f7ec6b6b32d3ae5d" }, "name" : "Drake U. Ryan", "address" : "Ap #804-1850 Orci Rd.", "city" : "Boise", "state" : "ID", "zip" : "89522", "phone" : "1-488-516-7771", "company" : "Enim Suspendisse Associates", "email" : "mi.lacinia.mattis@tinciduntDonecvitae.edu", "companyFax" : "1-672-981-6238", "companyAddress" : "Ap #395-6513 Accumsan Street", "companyCity" : "Pocatello", "companyState" : "OH", "companyZip" : "45198", "hireDate" : "11/03/2011" },{ "_id" : { "$oid" : "530124c9f7ec6b6b32d3ae5e" }, "name" : "April L. Potts", "address" : "168-2747 Ligula. Road", "city" : "Tallahassee", "state" : "Florida", "zip" : "40026", "phone" : "1-645-283-0150", "company" : "Neque Consulting", "email" : "eros.turpis@laciniamattisInteger.com", "companyFax" : "1-132-838-3529", "companyAddress" : "P.O. Box 633, 807 Non Road", "companyCity" : "St. Petersburg", "companyState" : "Texas", "companyZip" : "11343", "hireDate" : "03/08/2007" },{ "_id" : { "$oid" : "530124c9f7ec6b6b32d3ae5f" }, "name" : "Tana I. Hull", "address" : "5050 Elementum, St.", "city" : "Iowa City", "state" : "Iowa", "zip" : "98531", "phone" : "1-116-302-2948", "company" : "Aliquam PC", "email" : "leo@vulputaterisusa.co.uk", "companyFax" : "1-200-947-3684", "companyAddress" : "572-6790 Vitae, Rd.", "companyCity" : "Sioux City", "companyState" : "Wisconsin", "companyZip" : "16374", "hireDate" : "03/23/2006" },{ "_id" : { "$oid" : "530124c9f7ec6b6b32d3ae60" }, "name" : "Chloe F. Santos", "address" : "Ap #733-1736 Lorem. Rd.", "city" : "Grand Island", "state" : "NE", "zip" : "60916", "phone" : "1-772-649-0669", "company" : "Sit Amet LLC", "email" : "dolor@et.com", "companyFax" : "1-182-738-6765", "companyAddress" : "419-4006 Vel St.", "companyCity" : "Grand Island", "companyState" : "Wyoming", "companyZip" : "37506", "hireDate" : "03/12/2011" },{ "_id" : { "$oid" : "530124c9f7ec6b6b32d3ae61" }, "name" : "Tate A. Daniel", "address" : "Ap #969-6546 Ligula Avenue", "city" : "Aurora", "state" : "Colorado", "zip" : "54385", "phone" : "1-985-130-2667", "company" : "Primis In Faucibus LLC", "email" : "vel.convallis@Donec.net", "companyFax" : "1-675-553-9502", "companyAddress" : "588-3282 Cras Rd.", "companyCity" : "Lakewood", "companyState" : "MT", "companyZip" : "13297", "hireDate" : "06/13/2010" },{ "_id" : { "$oid" : "530124c9f7ec6b6b32d3ae62" }, "name" : "Rosalyn W. Pearson", "address" : "Ap #751-9435 Ut, St.", "city" : "Boston", "state" : "Massachusetts", "zip" : "47777", "phone" : "1-374-651-3632", "company" : "Ornare Libero At Institute", "email" : "est@risusat.org", "companyFax" : "1-760-464-3404", "companyAddress" : "4698 Et Rd.", "companyCity" : "Cambridge", "companyState" : "Vermont", "companyZip" : "18836", "hireDate" : "06/24/2008" },{ "_id" : { "$oid" : "530124c9f7ec6b6b32d3ae63" }, "name" : "Kylynn W. Fernandez", "address" : "Ap #142-1448 Quam, Av.", "city" : "Lakewood", "state" : "Colorado", "zip" : "11679", "phone" : "1-643-221-6704", "company" : "Ac Turpis Egestas Inc.", "email" : "massa.lobortis.ultrices@erat.edu", "companyFax" : "1-615-539-4407", "companyAddress" : "Ap #229-2440 Nascetur Avenue", "companyCity" : "Denver", "companyState" : "CA", "companyZip" : "78615", "hireDate" : "06/04/2012" },{ "_id" : { "$oid" : "530124c9f7ec6b6b32d3ae64" }, "name" : "Lenore J. Hawkins", "address" : "635-5408 Vitae St.", "city" : "Newark", "state" : "Delaware", "zip" : "71954", "phone" : "1-175-222-5308", "company" : "Scelerisque Neque Corporation", "email" : "ut.erat@feugiatmetussit.org", "companyFax" : "1-610-150-3041", "companyAddress" : "231-9699 Nunc Rd.", "companyCity" : "Dover", "companyState" : "MI", "companyZip" : "10969", "hireDate" : "11/01/2006" },{ "_id" : { "$oid" : "530124c9f7ec6b6b32d3ae65" }, "name" : "Jason W. Burris", "address" : "417-8813 Aenean Av.", "city" : "Kaneohe", "state" : "Hawaii", "zip" : "57610", "phone" : "1-923-327-6468", "company" : "Dolor Nulla Semper Corporation", "email" : "sed@facilisis.net", "companyFax" : "1-954-250-9503", "companyAddress" : "593-7774 Libero Street", "companyCity" : "Kapolei", "companyState" : "IL", "companyZip" : "34930", "hireDate" : "08/30/2007" },{ "_id" : { "$oid" : "530124c9f7ec6b6b32d3ae66" }, "name" : "Barrett D. Bernard", "address" : "604-9638 Id, St.", "city" : "Duluth", "state" : "MN", "zip" : "40282", "phone" : "1-629-112-3838", "company" : "Duis Sit Corporation", "email" : "cursus.vestibulum.Mauris@semPellentesque.edu", "companyFax" : "1-574-721-0142", "companyAddress" : "P.O. Box 572, 1508 Suspendisse Rd.", "companyCity" : "Minneapolis", "companyState" : "NV", "companyZip" : "25797", "hireDate" : "08/22/2012" },{ "_id" : { "$oid" : "530124c9f7ec6b6b32d3ae67" }, "name" : "Burke R. Holmes", "address" : "Ap #221-8346 Lectus Road", "city" : "Birmingham", "state" : "Alabama", "zip" : "36607", "phone" : "1-165-305-8716", "company" : "Metus Vivamus Company", "email" : "non.sollicitudin.a@aclibero.ca", "companyFax" : "1-623-666-2879", "companyAddress" : "138 A, Road", "companyCity" : "Birmingham", "companyState" : "Montana", "companyZip" : "35128", "hireDate" : "12/15/2007" },{ "_id" : { "$oid" : "530124c9f7ec6b6b32d3ae68" }, "name" : "Byron O. Beach", "address" : "Ap #435-2158 Curabitur Rd.", "city" : "Portland", "state" : "OR", "zip" : "24083", "phone" : "1-776-605-0407", "company" : "Gravida Sit Amet Institute", "email" : "fames@magnanecquam.com", "companyFax" : "1-392-136-8223", "companyAddress" : "842-2106 Nibh St.", "companyCity" : "Gresham", "companyState" : "UT", "companyZip" : "36266", "hireDate" : "09/29/2012" },{ "_id" : { "$oid" : "530124c9f7ec6b6b32d3ae69" }, "name" : "Brendan R. Nicholson", "address" : "731-9460 Mauris. St.", "city" : "Bear", "state" : "Delaware", "zip" : "27377", "phone" : "1-956-577-4220", "company" : "Malesuada Consulting", "email" : "molestie.arcu.Sed@pharetraQuisqueac.ca", "companyFax" : "1-146-256-9681", "companyAddress" : "Ap #160-418 Faucibus St.", "companyCity" : "Bear", "companyState" : "Illinois", "companyZip" : "14155", "hireDate" : "01/28/2014" },{ "_id" : { "$oid" : "530124c9f7ec6b6b32d3ae6a" }, "name" : "Georgia D. Ferrell", "address" : "Ap #279-963 Integer Av.", "city" : "West Valley City", "state" : "UT", "zip" : "78899", "phone" : "1-582-624-7934", "company" : "A Foundation", "email" : "a.dui@Nullamscelerisqueneque.net", "companyFax" : "1-534-874-5189", "companyAddress" : "Ap #903-2608 Sed Rd.", "companyCity" : "Provo", "companyState" : "Wyoming", "companyZip" : "42683", "hireDate" : "05/19/2008" },{ "_id" : { "$oid" : "530124c9f7ec6b6b32d3ae6b" }, "name" : "Noah T. Sargent", "address" : "1717 Leo. Rd.", "city" : "Gaithersburg", "state" : "MD", "zip" : "75110", "phone" : "1-588-848-7155", "company" : "Sem Consulting", "email" : "arcu@Crasdolordolor.ca", "companyFax" : "1-601-749-8759", "companyAddress" : "Ap #648-1559 Auctor Road", "companyCity" : "Frederick", "companyState" : "GA", "companyZip" : "47321", "hireDate" : "04/19/2006" },{ "_id" : { "$oid" : "530124c9f7ec6b6b32d3ae6c" }, "name" : "Zoe S. Hines", "address" : "7112 Mattis. Avenue", "city" : "Houston", "state" : "Texas", "zip" : "25456", "phone" : "1-505-910-0296", "company" : "Et Institute", "email" : "aliquam.enim@infaucibusorci.com", "companyFax" : "1-205-826-3907", "companyAddress" : "7290 Laoreet Rd.", "companyCity" : "Dallas", "companyState" : "AR", "companyZip" : "48872", "hireDate" : "03/05/2007" },{ "_id" : { "$oid" : "530124c9f7ec6b6b32d3ae6d" }, "name" : "Tucker V. Savage", "address" : "4714 Lorem Rd.", "city" : "Metairie", "state" : "LA", "zip" : "58094", "phone" : "1-562-316-8505", "company" : "Blandit Nam Nulla Incorporated", "email" : "nascetur.ridiculus.mus@nequeSed.ca", "companyFax" : "1-468-719-2277", "companyAddress" : "P.O. Box 732, 4799 Ante St.", "companyCity" : "New Orleans", "companyState" : "PA", "companyZip" : "93311", "hireDate" : "01/29/2011" },{ "_id" : { "$oid" : "530124c9f7ec6b6b32d3ae6e" }, "name" : "Jamalia C. Hatfield", "address" : "8142 Phasellus Avenue", "city" : "Fairbanks", "state" : "Alaska", "zip" : "99688", "phone" : "1-878-645-8737", "company" : "Nunc Pulvinar Arcu Company", "email" : "egestas@velvulputateeu.org", "companyFax" : "1-268-724-4714", "companyAddress" : "P.O. Box 714, 3783 Integer St.", "companyCity" : "Ketchikan", "companyState" : "Georgia", "companyZip" : "99934", "hireDate" : "11/22/2007" },{ "_id" : { "$oid" : "530124c9f7ec6b6b32d3ae6f" }, "name" : "Lucas D. Riggs", "address" : "Ap #739-9867 Curabitur Ave", "city" : "Burlington", "state" : "Vermont", "zip" : "94642", "phone" : "1-272-727-6199", "company" : "Magna Nec Associates", "email" : "a@sagittis.edu", "companyFax" : "1-843-411-7704", "companyAddress" : "7039 Sit Avenue", "companyCity" : "Colchester", "companyState" : "CO", "companyZip" : "76272", "hireDate" : "10/28/2009" },{ "_id" : { "$oid" : "530124c9f7ec6b6b32d3ae70" }, "name" : "Larissa I. Pennington", "address" : "6769 Sodales Ave", "city" : "Little Rock", "state" : "AR", "zip" : "72946", "phone" : "1-806-379-6150", "company" : "Gravida Aliquam Limited", "email" : "dis.parturient@lobortistellus.org", "companyFax" : "1-402-954-9215", "companyAddress" : "Ap #281-8404 Dui Rd.", "companyCity" : "Fayetteville", "companyState" : "Florida", "companyZip" : "72700", "hireDate" : "11/09/2009" },{ "_id" : { "$oid" : "530124c9f7ec6b6b32d3ae71" }, "name" : "Vernon J. Wong", "address" : "8117 Arcu. Rd.", "city" : "St. Petersburg", "state" : "Florida", "zip" : "62415", "phone" : "1-381-445-2882", "company" : "Duis Cursus Limited", "email" : "euismod@nisinibhlacinia.edu", "companyFax" : "1-777-596-3093", "companyAddress" : "4680 Lorem Street", "companyCity" : "St. Petersburg", "companyState" : "OK", "companyZip" : "70514", "hireDate" : "02/09/2014" },{ "_id" : { "$oid" : "530124c9f7ec6b6b32d3ae72" }, "name" : "Nash X. Merritt", "address" : "Ap #253-4084 A Ave", "city" : "Mobile", "state" : "AL", "zip" : "36700", "phone" : "1-360-988-7993", "company" : "Aliquam Iaculis LLP", "email" : "aliquam@nibh.edu", "companyFax" : "1-872-239-6598", "companyAddress" : "966-4460 Faucibus St.", "companyCity" : "Montgomery", "companyState" : "Mississippi", "companyZip" : "36699", "hireDate" : "01/03/2014" },{ "_id" : { "$oid" : "530124c9f7ec6b6b32d3ae73" }, "name" : "Abel G. Bond", "address" : "8904 Neque Street", "city" : "West Valley City", "state" : "Utah", "zip" : "73426", "phone" : "1-125-425-3006", "company" : "Ac Company", "email" : "a.feugiat.tellus@nequeNullam.org", "companyFax" : "1-456-485-0928", "companyAddress" : "630-4404 Dictum Ave", "companyCity" : "Provo", "companyState" : "MS", "companyZip" : "92637", "hireDate" : "06/10/2010" },{ "_id" : { "$oid" : "530124c9f7ec6b6b32d3ae74" }, "name" : "Irene E. Bond", "address" : "1129 Justo Street", "city" : "Burlington", "state" : "VT", "zip" : "87823", "phone" : "1-621-660-0641", "company" : "Aenean Company", "email" : "Integer.urna@Aliquamvulputateullamcorper.co.uk", "companyFax" : "1-286-587-1265", "companyAddress" : "7412 Proin Avenue", "companyCity" : "Essex", "companyState" : "Wisconsin", "companyZip" : "59079", "hireDate" : "07/03/2009" },{ "_id" : { "$oid" : "530124c9f7ec6b6b32d3ae75" }, "name" : "Maxwell W. Lawson", "address" : "7226 Magna. St.", "city" : "Akron", "state" : "Ohio", "zip" : "31081", "phone" : "1-237-849-0860", "company" : "Enim Consequat Purus LLC", "email" : "a.arcu@ultricesDuisvolutpat.ca", "companyFax" : "1-465-821-6004", "companyAddress" : "P.O. Box 626, 2238 Ante. St.", "companyCity" : "Akron", "companyState" : "Tennessee", "companyZip" : "17525", "hireDate" : "10/12/2009" },{ "_id" : { "$oid" : "530124c9f7ec6b6b32d3ae76" }, "name" : "Phelan P. Byrd", "address" : "483-9768 In Rd.", "city" : "Kansas City", "state" : "MO", "zip" : "27475", "phone" : "1-159-484-1937", "company" : "Risus Nunc Ac LLC", "email" : "lorem.auctor.quis@maurisblandit.ca", "companyFax" : "1-899-176-4239", "companyAddress" : "310-3763 Mi St.", "companyCity" : "Jefferson City", "companyState" : "MS", "companyZip" : "18724", "hireDate" : "10/30/2008" },{ "_id" : { "$oid" : "530124c9f7ec6b6b32d3ae77" }, "name" : "Calvin O. Fowler", "address" : "3219 Lacus. Rd.", "city" : "Rutland", "state" : "Vermont", "zip" : "41062", "phone" : "1-442-772-2191", "company" : "Euismod Mauris Limited", "email" : "sapien.cursus.in@lorem.co.uk", "companyFax" : "1-476-895-2197", "companyAddress" : "P.O. Box 311, 412 Mi. Rd.", "companyCity" : "Rutland", "companyState" : "Maine", "companyZip" : "13649", "hireDate" : "08/11/2005" },{ "_id" : { "$oid" : "530124c9f7ec6b6b32d3ae78" }, "name" : "Myra Z. Wilkerson", "address" : "Ap #848-2830 Eget St.", "city" : "Eugene", "state" : "Oregon", "zip" : "16022", "phone" : "1-621-253-6443", "company" : "At Inc.", "email" : "libero.Donec@egestasurnajusto.net", "companyFax" : "1-441-212-5844", "companyAddress" : "6287 Semper Rd.", "companyCity" : "Salem", "companyState" : "WA", "companyZip" : "87017", "hireDate" : "09/28/2009" },{ "_id" : { "$oid" : "530124c9f7ec6b6b32d3ae79" }, "name" : "Brielle M. Guy", "address" : "6021 Laoreet Rd.", "city" : "Shreveport", "state" : "Louisiana", "zip" : "20643", "phone" : "1-587-164-4640", "company" : "Luctus Et Ultrices Institute", "email" : "feugiat@a.co.uk", "companyFax" : "1-263-841-3249", "companyAddress" : "1491 Quisque St.", "companyCity" : "Metairie", "companyState" : "Tennessee", "companyZip" : "81819", "hireDate" : "10/04/2009" },{ "_id" : { "$oid" : "530124c9f7ec6b6b32d3ae7a" }, "name" : "Erich C. Fisher", "address" : "Ap #630-6125 Pretium Rd.", "city" : "Frankfort", "state" : "KY", "zip" : "84252", "phone" : "1-444-794-0949", "company" : "Porttitor Corp.", "email" : "rutrum.eu@rutrumurna.net", "companyFax" : "1-941-117-9035", "companyAddress" : "Ap #389-4206 Arcu. Road", "companyCity" : "Frankfort", "companyState" : "Pennsylvania", "companyZip" : "56600", "hireDate" : "09/21/2007" },{ "_id" : { "$oid" : "530124c9f7ec6b6b32d3ae7b" }, "name" : "Vanna V. Santana", "address" : "1008 Erat Av.", "city" : "Davenport", "state" : "IA", "zip" : "94328", "phone" : "1-932-152-8359", "company" : "Nam Ac Nulla LLP", "email" : "ante.Maecenas.mi@Aeneaneuismodmauris.co.uk", "companyFax" : "1-340-844-9284", "companyAddress" : "847-5103 Convallis St.", "companyCity" : "Des Moines", "companyState" : "Idaho", "companyZip" : "77474", "hireDate" : "10/14/2007" },{ "_id" : { "$oid" : "530124c9f7ec6b6b32d3ae7c" }, "name" : "Flynn P. Lucas", "address" : "Ap #151-7979 Amet Ave", "city" : "Indianapolis", "state" : "IN", "zip" : "27520", "phone" : "1-150-368-5053", "company" : "Erat Nonummy Ultricies Foundation", "email" : "sem.semper@tincidunt.edu", "companyFax" : "1-100-924-2595", "companyAddress" : "376 Pede, Rd.", "companyCity" : "South Bend", "companyState" : "TX", "companyZip" : "75845", "hireDate" : "02/13/2006" },{ "_id" : { "$oid" : "530124c9f7ec6b6b32d3ae7d" }, "name" : "Brett B. Guzman", "address" : "3084 Ipsum St.", "city" : "Salem", "state" : "OR", "zip" : "47001", "phone" : "1-769-650-4876", "company" : "Scelerisque Neque Corporation", "email" : "neque.et.nunc@sitametconsectetuer.edu", "companyFax" : "1-336-239-5978", "companyAddress" : "P.O. Box 976, 226 Phasellus Rd.", "companyCity" : "Salem", "companyState" : "Arkansas", "companyZip" : "17972", "hireDate" : "05/23/2005" }]
